clusterlogger/__init__.py
clusterlogger/handler.py
clusterlogger/logfilter.py
clusterlogger-0.2.0.dist-info/top_level.txt
clusterlogger-0.2.0.dist-info/METADATA
clusterlogger-0.2.0.dist-info/DESCRIPTION.rst
clusterlogger-0.2.0.dist-info/metadata.json
clusterlogger-0.2.0.dist-info/WHEEL
clusterlogger-0.2.0.dist-info/RECORD
