Metadata-Version: 2.0
Name: clusterlogger
Version: 0.2.0
Summary: Logging package for contextual information of clusters.
Home-page: https://github.com/RayCrafter/clusterlogger
Author: David Zuber
Author-email: zuber.david@gmx.de
License: BSD
Keywords: clusterlogger
Platform: UNKNOWN
Classifier: Development Status :: 2 - Pre-Alpha
Classifier: Intended Audience :: Developers
Classifier: License :: OSI Approved :: BSD License
Classifier: Natural Language :: English
Classifier: Programming Language :: Python :: 2.7
Requires-Dist: graypy
